brAsHelpIndexGenerator/__init__.py
brAsHelpIndexGenerator/docBuilder.py
brAsHelpIndexGenerator/plugin.py
brAsHelpIndexGenerator/Templates/HelpUpgradeTemplate.xml
brAsHelpIndexGenerator/Templates/helpContentsTemplate.xml
BRAsHelpIndexGenerator-1.0.0.dist-info/LICENSE
BRAsHelpIndexGenerator-1.0.0.dist-info/METADATA
BRAsHelpIndexGenerator-1.0.0.dist-info/WHEEL
BRAsHelpIndexGenerator-1.0.0.dist-info/entry_points.txt
BRAsHelpIndexGenerator-1.0.0.dist-info/top_level.txt
BRAsHelpIndexGenerator-1.0.0.dist-info/RECORD
